<?xml version="1.0" encoding="utf-8" ?>
<dwsync>
<file name="add.php" server="10.10.10.22/hr-cms/" local="131634975189334662" remote="131634975600000000" />
<file name="index.php" server="10.10.10.22/hr-cms/" local="131455318810490831" remote="131455318800000000" />
<file name="add.php" server="10.10.10.33/hr-cms/" local="131634962042412109" remote="131634964200000000" />
<file name="honor.php" server="10.10.10.33/hr-cms/" local="131370912000000000" remote="131370912000000000" />
<file name="honoradd.php" server="10.10.10.33/hr-cms/" local="131376960000000000" remote="131376960000000000" />
<file name="index.php" server="10.10.10.33/hr-cms/" local="131454720000000000" remote="131454720000000000" />
<file name="list.php" server="10.10.10.33/hr-cms/" local="131376960000000000" remote="131376960000000000" />
<file name="type.php" server="10.10.10.33/hr-cms/" local="131351040000000000" remote="131351040000000000" />
</dwsync>